autoboto/__init__.py
autoboto/versions.py
autoboto/core/__init__.py
autoboto/core/client.py
autoboto/core/shapes.py
autoboto/core/type_info.py
autoboto/examples/__init__.py
autoboto/examples/try_cloudformation.py
autoboto/examples/try_s3.py
autoboto/services/__init__.py
autoboto/services/acm/__init__.py
autoboto/services/acm/client.py
autoboto/services/acm/shapes.py
autoboto/services/acm-pca/__init__.py
autoboto/services/acm-pca/client.py
autoboto/services/acm-pca/shapes.py
autoboto/services/alexaforbusiness/__init__.py
autoboto/services/alexaforbusiness/client.py
autoboto/services/alexaforbusiness/shapes.py
autoboto/services/apigateway/__init__.py
autoboto/services/apigateway/client.py
autoboto/services/apigateway/shapes.py
autoboto/services/application-autoscaling/__init__.py
autoboto/services/application-autoscaling/client.py
autoboto/services/application-autoscaling/shapes.py
autoboto/services/appstream/__init__.py
autoboto/services/appstream/client.py
autoboto/services/appstream/shapes.py
autoboto/services/appsync/__init__.py
autoboto/services/appsync/client.py
autoboto/services/appsync/shapes.py
autoboto/services/athena/__init__.py
autoboto/services/athena/client.py
autoboto/services/athena/shapes.py
autoboto/services/autoscaling/__init__.py
autoboto/services/autoscaling/client.py
autoboto/services/autoscaling/shapes.py
autoboto/services/autoscaling-plans/__init__.py
autoboto/services/autoscaling-plans/client.py
autoboto/services/autoscaling-plans/shapes.py
autoboto/services/batch/__init__.py
autoboto/services/batch/client.py
autoboto/services/batch/shapes.py
autoboto/services/budgets/__init__.py
autoboto/services/budgets/client.py
autoboto/services/budgets/shapes.py
autoboto/services/ce/__init__.py
autoboto/services/ce/client.py
autoboto/services/ce/shapes.py
autoboto/services/cloud9/__init__.py
autoboto/services/cloud9/client.py
autoboto/services/cloud9/shapes.py
autoboto-0.4.3.dist-info/METADATA
autoboto-0.4.3.dist-info/RECORD
autoboto-0.4.3.dist-info/WHEEL
autoboto-0.4.3.dist-info/top_level.txt
