Metadata-Version: 2.1
Name: autoboto
Version: 0.4.3
Summary: boto3 with auto-complete and dataclasses not dicts
Home-page: https://github.com/jbasko/autoboto
Author: Jazeps Basko
Author-email: jazeps.basko@gmail.com
Maintainer: Jazeps Basko
Maintainer-email: jazeps.basko@gmail.com
License: MIT
Platform: UNKNOWN
Classifier: Development Status :: 3 - Alpha
Classifier: Intended Audience :: Developers
Classifier: Programming Language :: Python
Classifier: Programming Language :: Python :: 3
Classifier: Programming Language :: Python :: 3.6
Classifier: Programming Language :: Python :: 3.7
Classifier: License :: OSI Approved :: MIT License
Requires-Python: >=3.6.0
Provides-Extra: botogen
Requires-Dist: boto3
Requires-Dist: dataclasses
Requires-Dist: typing-inspect
Provides-Extra: botogen
Requires-Dist: botocore; extra == 'botogen'
Requires-Dist: html2text (==2018.1.9); extra == 'botogen'
Requires-Dist: wr-profiles (<5.0,>=4.0.0); extra == 'botogen'
Requires-Dist: yapf (==0.23.0); extra == 'botogen'
